requirements.txt
witrn/__init__.py
witrn/driver/__init__.py
witrn/driver/binutils.py
witrn/driver/protocol.py
witrn_driver-0.1.2.dist-info/LICENSE
witrn_driver-0.1.2.dist-info/METADATA
witrn_driver-0.1.2.dist-info/WHEEL
witrn_driver-0.1.2.dist-info/top_level.txt
witrn_driver-0.1.2.dist-info/zip-safe
witrn_driver-0.1.2.dist-info/RECORD
