Metadata-Version: 2.1
Name: witrn-driver
Version: 0.1.2
Summary: Driver for reading data from modern WITRN meters
Author: didim99
Project-URL: Source, https://github.com/didim99/witrn-driver
Platform: any
Requires-Python: >=3.8
License-File: LICENSE
Requires-Dist: pyusb~=1.2.1
